{
  "config_type": "sldl.release_check",
  "description": "SLDL v1.0.13 release quality check target with CI workflow coverage",
  "version": "1.0.13",
  "base_dir": "..",
  "required_files": [
    "README.md",
    "CHANGELOG.md",
    ".gitignore",
    "docs/index.md",
    "docs/getting_started.md",
    "docs/sldl_language_reference.md",
    "docs/document_model.md",
    "docs/project_workflow.md",
    "docs/config_reference.md",
    "docs/commands_reference.md",
    "docs/github_repository_guide.md",
    "docs/v1_0_release_notes.md",
    "docs/bilingual_documentation.md",
    "docs/compatibility_policy.md",
    "docs/migration_guide_v0_to_v1.md",
    "docs/known_limitations.md",
    "docs/release_process.md",
    "docs/version_reset_policy.md",
    "docs/ja/index.md",
    "docs/ja/getting_started.md",
    "docs/ja/sldl_language_reference.md",
    "docs/ja/document_model.md",
    "docs/ja/project_workflow.md",
    "docs/ja/config_reference.md",
    "docs/ja/commands_reference.md",
    "docs/ja/github_repository_guide.md",
    "docs/ja/known_limitations.md",
    "docs/ja/release_process.md",
    "docs/ja/compatibility_policy.md",
    "docs/ja/v1_0_release_notes.md",
    "docs/ja/bilingual_documentation.md",
    "examples/README.md",
    "examples/official_project_overview_en.sldl",
    "examples/official_project_overview_ja.sldl",
    "examples/research_report_en.sldl",
    "examples/research_report_ja.sldl",
    "examples/sldl_schema.json",
    "examples/project_official_examples.json",
    "examples/export_labels_en.json",
    "examples/export_labels_ja.json",
    "examples/latex_build_platex_dvipdfmx.json",
    "examples/latex_build_platex_dvipdfmx_dry_run.json",
    "examples/release_check.json",
    "examples/golden_snapshot.json",
    "sldl_compiler/quality.py",
    "sldl_compiler/cli.py",
    "tests/test_v1_ready_workflow.py",
    "templates/template_manifest.json",
    "templates/manifest.json",
    "templates/research_report_en.sldl",
    "templates/research_report_ja.sldl",
    "templates/project_overview_en.sldl",
    "templates/project_overview_ja.sldl",
    "docs/template_schema_binding.md",
    "docs/ja/template_schema_binding.md",
    "tests/test_template_schema_binding.py",
    "examples/template_schema_binding_project.json",
    "examples/template_schema_binding_report.sldl",
    "docs/v1_0_1_release_notes.md",
    "docs/ja/v1_0_1_release_notes.md",
    "docs/v1_0_2_release_notes.md",
    "docs/ja/v1_0_2_release_notes.md",
    "examples/template_schema_binding_failure_project.json",
    "docs/v1_0_3_release_notes.md",
    "docs/ja/v1_0_3_release_notes.md",
    "docs/v1_0_4_release_notes.md",
    "docs/ja/v1_0_4_release_notes.md",
    "docs/template_manifest_migration.md",
    "docs/ja/template_manifest_migration.md",
    "docs/generated_template_reference.md",
    "docs/ja/generated_template_reference.md",
    "docs/v1_0_5_release_notes.md",
    "docs/ja/v1_0_5_release_notes.md",
    "docs/generated_template_reference.json",
    "docs/v1_0_6_release_notes.md",
    "docs/ja/v1_0_6_release_notes.md",
    "docs/v1_0_7_release_notes.md",
    "docs/ja/v1_0_7_release_notes.md",
    "docs/v1_0_8_release_notes.md",
    "docs/ja/v1_0_8_release_notes.md",
    "examples/template_manifest_bad_missing_schema.json",
    "examples/template_manifest_bad_wrong_config_type.json",
    "examples/template_manifest_bad_missing_template.json",
    "docs/v1_0_9_release_notes.md",
    "docs/ja/v1_0_9_release_notes.md",
    "docs/diagnostics_reference.md",
    "docs/ja/diagnostics_reference.md",
    "docs/diagnostics_reference.json",
    "sldl_compiler/diagnostic_reference.py",
    "tests/test_diagnostics_reference.py",
    "docs/v1_0_10_release_notes.md",
    "docs/ja/v1_0_10_release_notes.md",
    "docs/reference_index.md",
    "docs/ja/reference_index.md",
    "docs/reference_index.json",
    "docs/cli_help_reference.md",
    "docs/ja/cli_help_reference.md",
    "docs/cli_help_reference.json",
    "sldl_compiler/reference_docs.py",
    "tests/test_reference_docs.py",
    "docs/v1_0_11_release_notes.md",
    "docs/ja/v1_0_11_release_notes.md",
    "docs/release_report.md",
    "docs/ja/release_report.md",
    "docs/release_report.json",
    "sldl_compiler/release_report.py",
    "tests/test_release_report.py",
    "docs/v1_0_12_release_notes.md",
    "docs/ja/v1_0_12_release_notes.md",
    "docs/release_summary.json",
    ".github/workflows/test.yml",
    ".github/workflows/release-check.yml",
    "docs/ci_workflow.md",
    "docs/ja/ci_workflow.md",
    "docs/v1_0_13_release_notes.md",
    "docs/ja/v1_0_13_release_notes.md"
  ],
  "forbidden_paths": [
    "docs/bilingual_release_preparation.md",
    "docs/reset_preparation.md",
    "docs/v1_0_release_candidate_plan.md",
    "examples/archive"
  ],
  "forbidden_globs": [
    "build/v0*",
    "docs/sldl_v0_*",
    "docs/v0_*",
    "examples/v0*",
    "examples/v1[0-9]*",
    "examples/archive*",
    "tests/test_v0*.py",
    "tests/test_v1[0-5]*.py",
    "docs/*release_candidate*",
    "docs/*_preparation.md"
  ],
  "config_files": [
    "examples/export_labels_en.json",
    "examples/export_labels_ja.json",
    "examples/latex_build_platex_dvipdfmx_dry_run.json",
    "examples/latex_build_platex_dvipdfmx.json",
    "examples/sldl_schema.json",
    "examples/project_official_examples.json",
    "examples/release_check.json",
    "examples/golden_snapshot.json",
    "templates/template_manifest.json",
    "examples/template_schema_binding_failure_project.json",
    "templates/manifest.json",
    "docs/generated_template_reference.json",
    "docs/diagnostics_reference.json",
    "docs/reference_index.json",
    "docs/cli_help_reference.json",
    "docs/release_report.json",
    "docs/release_summary.json",
    "examples/release_summary_smoke_check.json"
  ],
  "commands": [
    {
      "name": "template-list",
      "args": [
        "template",
        "list"
      ],
      "category": "core-cli",
      "severity": "error"
    },
    {
      "name": "template-explain-research-report-en",
      "args": [
        "template",
        "explain",
        "research_report_en"
      ],
      "category": "core-cli",
      "severity": "error"
    },
    {
      "name": "template-explain-research-report-en-markdown",
      "args": [
        "template",
        "explain",
        "research_report_en",
        "--format",
        "markdown"
      ],
      "category": "core-cli",
      "severity": "error"
    },
    {
      "name": "template-explain-research-report-en-json",
      "args": [
        "template",
        "explain",
        "research_report_en",
        "--format",
        "json"
      ],
      "category": "core-cli",
      "severity": "error"
    },
    {
      "name": "template-docs-markdown",
      "args": [
        "template",
        "docs",
        "--format",
        "markdown"
      ],
      "category": "generated-reference",
      "severity": "error"
    },
    {
      "name": "template-docs-json",
      "args": [
        "template",
        "docs",
        "--format",
        "json"
      ],
      "category": "generated-reference",
      "severity": "error"
    },
    {
      "name": "template-docs-markdown-check",
      "args": [
        "template",
        "docs",
        "--format",
        "markdown",
        "--check",
        "docs/generated_template_reference.md"
      ],
      "category": "generated-reference",
      "severity": "error"
    },
    {
      "name": "template-docs-markdown-ja-check",
      "args": [
        "template",
        "docs",
        "--format",
        "markdown",
        "--language",
        "ja",
        "--check",
        "docs/ja/generated_template_reference.md"
      ],
      "category": "generated-reference",
      "severity": "error"
    },
    {
      "name": "template-docs-json-check",
      "args": [
        "template",
        "docs",
        "--format",
        "json",
        "--check",
        "docs/generated_template_reference.json"
      ],
      "category": "generated-reference",
      "severity": "error"
    },
    {
      "name": "diagnostics-list",
      "args": [
        "diagnostics",
        "list"
      ],
      "category": "diagnostics",
      "severity": "error"
    },
    {
      "name": "diagnostics-list-json",
      "args": [
        "diagnostics",
        "list",
        "--json"
      ],
      "category": "diagnostics",
      "severity": "error"
    },
    {
      "name": "diagnostics-docs-markdown",
      "args": [
        "diagnostics",
        "docs",
        "--format",
        "markdown"
      ],
      "category": "generated-reference",
      "severity": "error"
    },
    {
      "name": "diagnostics-docs-json",
      "args": [
        "diagnostics",
        "docs",
        "--format",
        "json"
      ],
      "category": "generated-reference",
      "severity": "error"
    },
    {
      "name": "diagnostics-docs-markdown-check",
      "args": [
        "diagnostics",
        "docs",
        "--format",
        "markdown",
        "--check",
        "docs/diagnostics_reference.md"
      ],
      "category": "generated-reference",
      "severity": "error"
    },
    {
      "name": "diagnostics-docs-markdown-ja-check",
      "args": [
        "diagnostics",
        "docs",
        "--format",
        "markdown",
        "--language",
        "ja",
        "--check",
        "docs/ja/diagnostics_reference.md"
      ],
      "category": "generated-reference",
      "severity": "error"
    },
    {
      "name": "diagnostics-docs-json-check",
      "args": [
        "diagnostics",
        "docs",
        "--format",
        "json",
        "--check",
        "docs/diagnostics_reference.json"
      ],
      "category": "generated-reference",
      "severity": "error"
    },
    {
      "name": "config-explain-diagnostics-reference",
      "args": [
        "config",
        "explain",
        "sldl.diagnostics_reference"
      ],
      "category": "config",
      "severity": "error"
    },
    {
      "name": "reference-index-markdown",
      "args": [
        "reference",
        "index",
        "--format",
        "markdown"
      ],
      "category": "generated-reference",
      "severity": "error"
    },
    {
      "name": "reference-index-json",
      "args": [
        "reference",
        "index",
        "--format",
        "json"
      ],
      "category": "generated-reference",
      "severity": "error"
    },
    {
      "name": "reference-index-markdown-check",
      "args": [
        "reference",
        "index",
        "--format",
        "markdown",
        "--check",
        "docs/reference_index.md"
      ],
      "category": "generated-reference",
      "severity": "error"
    },
    {
      "name": "reference-index-markdown-ja-check",
      "args": [
        "reference",
        "index",
        "--format",
        "markdown",
        "--language",
        "ja",
        "--check",
        "docs/ja/reference_index.md"
      ],
      "category": "generated-reference",
      "severity": "error"
    },
    {
      "name": "reference-index-json-check",
      "args": [
        "reference",
        "index",
        "--format",
        "json",
        "--check",
        "docs/reference_index.json"
      ],
      "category": "generated-reference",
      "severity": "error"
    },
    {
      "name": "reference-cli-help-markdown",
      "args": [
        "reference",
        "cli-help",
        "--format",
        "markdown"
      ],
      "category": "generated-reference",
      "severity": "error"
    },
    {
      "name": "reference-cli-help-json",
      "args": [
        "reference",
        "cli-help",
        "--format",
        "json"
      ],
      "category": "generated-reference",
      "severity": "error"
    },
    {
      "name": "reference-cli-help-markdown-check",
      "args": [
        "reference",
        "cli-help",
        "--format",
        "markdown",
        "--check",
        "docs/cli_help_reference.md"
      ],
      "category": "generated-reference",
      "severity": "error"
    },
    {
      "name": "reference-cli-help-markdown-ja-check",
      "args": [
        "reference",
        "cli-help",
        "--format",
        "markdown",
        "--language",
        "ja",
        "--check",
        "docs/ja/cli_help_reference.md"
      ],
      "category": "generated-reference",
      "severity": "error"
    },
    {
      "name": "reference-cli-help-json-check",
      "args": [
        "reference",
        "cli-help",
        "--format",
        "json",
        "--check",
        "docs/cli_help_reference.json"
      ],
      "category": "generated-reference",
      "severity": "error"
    },
    {
      "name": "config-explain-reference-index",
      "args": [
        "config",
        "explain",
        "sldl.reference_index"
      ],
      "category": "config",
      "severity": "error"
    },
    {
      "name": "config-explain-cli-help-reference",
      "args": [
        "config",
        "explain",
        "sldl.cli_help_reference"
      ],
      "category": "config",
      "severity": "error"
    },
    {
      "name": "project-check-template-binding-negative-example",
      "args": [
        "project",
        "check",
        "examples/template_schema_binding_failure_project.json"
      ],
      "expect_failure": true,
      "category": "negative-example",
      "severity": "warning"
    },
    {
      "name": "check-missing-schema-diagnostic-negative-example",
      "args": [
        "check",
        "examples/research_report_en.sldl",
        "--schema",
        "examples/missing_schema.json"
      ],
      "expect_failure": true,
      "category": "negative-example",
      "severity": "warning"
    },
    {
      "name": "check-wrong-schema-config-type-negative-example",
      "args": [
        "check",
        "examples/research_report_en.sldl",
        "--schema",
        "examples/export_labels_en.json"
      ],
      "expect_failure": true,
      "category": "negative-example",
      "severity": "warning"
    },
    {
      "name": "config-check-template-manifest-missing-schema-negative-example",
      "args": [
        "config",
        "check",
        "examples/template_manifest_bad_missing_schema.json"
      ],
      "expect_failure": true,
      "category": "negative-example",
      "severity": "warning"
    },
    {
      "name": "config-check-template-manifest-wrong-config-type-negative-example",
      "args": [
        "config",
        "check",
        "examples/template_manifest_bad_wrong_config_type.json"
      ],
      "expect_failure": true,
      "category": "negative-example",
      "severity": "warning"
    },
    {
      "name": "config-check-template-manifest-missing-template-negative-example",
      "args": [
        "config",
        "check",
        "examples/template_manifest_bad_missing_template.json"
      ],
      "expect_failure": true,
      "category": "negative-example",
      "severity": "warning"
    },
    {
      "name": "schema-check",
      "args": [
        "schema",
        "check",
        "examples/sldl_schema.json"
      ],
      "category": "config",
      "severity": "error"
    },
    {
      "name": "config-list",
      "args": [
        "config",
        "list"
      ],
      "category": "config",
      "severity": "error"
    },
    {
      "name": "config-explain-project",
      "args": [
        "config",
        "explain",
        "sldl.project"
      ],
      "category": "config",
      "severity": "error"
    },
    {
      "name": "config-explain-release-check",
      "args": [
        "config",
        "explain",
        "sldl.release_check"
      ],
      "category": "config",
      "severity": "error"
    },
    {
      "name": "grammar",
      "args": [
        "grammar"
      ],
      "category": "core-cli",
      "severity": "error"
    },
    {
      "name": "template-project-help",
      "args": [
        "template",
        "project",
        "--help"
      ],
      "category": "template-workflow",
      "severity": "error"
    },
    {
      "name": "check-overview-en",
      "args": [
        "check",
        "examples/official_project_overview_en.sldl",
        "--schema",
        "examples/sldl_schema.json"
      ],
      "category": "template-workflow",
      "severity": "error"
    },
    {
      "name": "check-overview-ja",
      "args": [
        "check",
        "examples/official_project_overview_ja.sldl",
        "--schema",
        "examples/sldl_schema.json"
      ],
      "category": "template-workflow",
      "severity": "error"
    },
    {
      "name": "check-report-en",
      "args": [
        "check",
        "examples/research_report_en.sldl",
        "--schema",
        "examples/sldl_schema.json"
      ],
      "category": "template-workflow",
      "severity": "error"
    },
    {
      "name": "check-report-ja",
      "args": [
        "check",
        "examples/research_report_ja.sldl",
        "--schema",
        "examples/sldl_schema.json"
      ],
      "category": "template-workflow",
      "severity": "error"
    },
    {
      "name": "config-explain-template-manifest",
      "args": [
        "config",
        "explain",
        "sldl.template_manifest"
      ],
      "category": "config",
      "severity": "error"
    },
    {
      "name": "template-check-research-report-en",
      "args": [
        "template",
        "check",
        "research_report_en"
      ],
      "category": "template-workflow",
      "severity": "error"
    },
    {
      "name": "template-check-research-report-ja",
      "args": [
        "template",
        "check",
        "research_report_ja"
      ],
      "category": "template-workflow",
      "severity": "error"
    },
    {
      "name": "template-check-minutes",
      "args": [
        "template",
        "check",
        "minutes"
      ],
      "category": "template-workflow",
      "severity": "error"
    },
    {
      "name": "template-project-schema-bound",
      "args": [
        "template",
        "project",
        "research_report_en",
        "-o",
        "examples/template_schema_binding_project.json",
        "--document-output",
        "examples/template_schema_binding_report.sldl",
        "--force",
        "--formats",
        "markdown,html,latex,pdf",
        "--build-dir",
        "../build/template_schema_binding"
      ],
      "category": "template-workflow",
      "severity": "error"
    },
    {
      "name": "template-check-help",
      "args": [
        "template",
        "check",
        "--help"
      ],
      "category": "template-workflow",
      "severity": "error"
    },
    {
      "name": "template-docs-help",
      "args": [
        "template",
        "docs",
        "--help"
      ],
      "category": "generated-reference",
      "severity": "error"
    },
    {
      "name": "quality-report-markdown",
      "args": [
        "quality",
        "report",
        "build/release_manifest.json",
        "--format",
        "markdown"
      ],
      "category": "release-report",
      "severity": "error"
    },
    {
      "name": "quality-report-json",
      "args": [
        "quality",
        "report",
        "build/release_manifest.json",
        "--format",
        "json"
      ],
      "category": "release-report",
      "severity": "error"
    },
    {
      "name": "quality-report-markdown-check",
      "args": [
        "quality",
        "report",
        "build/release_manifest.json",
        "--format",
        "markdown",
        "--check",
        "docs/release_report.md"
      ],
      "category": "release-report",
      "severity": "error"
    },
    {
      "name": "quality-report-markdown-ja-check",
      "args": [
        "quality",
        "report",
        "build/release_manifest.json",
        "--format",
        "markdown",
        "--language",
        "ja",
        "--check",
        "docs/ja/release_report.md"
      ],
      "category": "release-report",
      "severity": "error"
    },
    {
      "name": "quality-report-json-check",
      "args": [
        "quality",
        "report",
        "build/release_manifest.json",
        "--format",
        "json",
        "--check",
        "docs/release_report.json"
      ],
      "category": "release-report",
      "severity": "error"
    },
    {
      "name": "config-explain-release-report",
      "args": [
        "config",
        "explain",
        "sldl.release_report"
      ],
      "category": "release-report",
      "severity": "error"
    },
    {
      "name": "quality-release-summary-smoke",
      "category": "release-summary",
      "severity": "error",
      "args": [
        "quality",
        "release",
        "--targets",
        "examples/release_summary_smoke_check.json",
        "--manifest",
        "build/release_summary_smoke_manifest.json",
        "--summary-json",
        "build/release_summary_smoke.json"
      ]
    },
    {
      "name": "config-explain-release-summary",
      "category": "release-summary",
      "severity": "info",
      "args": [
        "config",
        "explain",
        "sldl.release_summary"
      ]
    },
    {
      "name": "quality-release-summary-strict-smoke",
      "category": "ci-workflow",
      "severity": "error",
      "args": [
        "quality",
        "release",
        "--targets",
        "examples/release_summary_smoke_check.json",
        "--manifest",
        "build/release_summary_smoke_manifest.json",
        "--summary-json",
        "build/release_summary_smoke.json",
        "--fail-on-warning"
      ]
    }
  ],
  "project_files": [
    "examples/project_official_examples.json",
    "examples/template_schema_binding_project.json"
  ],
  "build_project_files": [
    "examples/project_official_examples.json",
    "examples/template_schema_binding_project.json"
  ],
  "build_manifest_files": [
    "build/official_examples/sldl_build_manifest.json",
    "build/template_schema_binding/sldl_build_manifest.json"
  ],
  "golden_snapshot": "examples/golden_snapshot.json",
  "compileall": true,
  "compile_paths": [
    "sldl_compiler",
    "tests/test_v1_ready_workflow.py",
    "tests/test_template_schema_binding.py",
    "tests/test_diagnostics_reference.py",
    "tests/test_reference_docs.py",
    "tests/test_release_report.py",
    "tests/test_ci_workflow.py"
  ]
}
